atec/__init__.py
atec/model.py
atec/run.py
atec_gdy-0.0.2.dist-info/METADATA
atec_gdy-0.0.2.dist-info/WHEEL
atec_gdy-0.0.2.dist-info/top_level.txt
atec_gdy-0.0.2.dist-info/RECORD
