Metadata-Version: 2.1
Name: atec_gdy
Version: 0.0.2
Summary: atec_gdy
Home-page: https://zhuanlan.zhihu.com/p/26159930
Author: xxx
Author-email: xxx@qq.com
License: UNKNOWN
Platform: UNKNOWN
